setup.py
md_prob_distributions/Binomialdistribution.py
md_prob_distributions/Gaussiandistribution.py
md_prob_distributions/Generaldistribution.py
md_prob_distributions/__init__.py
md_prob_distributions.egg-info/PKG-INFO
md_prob_distributions.egg-info/SOURCES.txt
md_prob_distributions.egg-info/dependency_links.txt
md_prob_distributions.egg-info/not-zip-safe
md_prob_distributions.egg-info/top_level.txt